xcsc_tushare/__init__.py
xcsc_tushare/client.py
xcsc_tushare/data_pro.py
xcsc_tushare/upass.py
xcsc_tushare-1.0.3.dist-info/LICENSE.txt
xcsc_tushare-1.0.3.dist-info/METADATA
xcsc_tushare-1.0.3.dist-info/WHEEL
xcsc_tushare-1.0.3.dist-info/top_level.txt
xcsc_tushare-1.0.3.dist-info/RECORD
